MANIFEST.in
README.md
setup.py
django_graphos.egg-info/PKG-INFO
django_graphos.egg-info/SOURCES.txt
django_graphos.egg-info/dependency_links.txt
django_graphos.egg-info/not-zip-safe
django_graphos.egg-info/top_level.txt
graphos/__init__.py
graphos/encoders.py
graphos/exceptions.py
graphos/models.py
graphos/tests.py
graphos/utils.py
graphos/views.py
graphos/renderers/__init__.py
graphos/renderers/base.py
graphos/renderers/c3js.py
graphos/renderers/flot.py
graphos/renderers/gchart.py
graphos/renderers/highcharts.py
graphos/renderers/matplotlib_renderer.py
graphos/renderers/morris.py
graphos/renderers/yui.py
graphos/sources/__init__.py
graphos/sources/base.py
graphos/sources/csv_file.py
graphos/sources/model.py
graphos/sources/mongo.py
graphos/sources/simple.py
graphos/templates/graphos/as_html.html
graphos/templates/graphos/model_template.html
graphos/templates/graphos/redis_template.html
graphos/templates/graphos/c3js/html.html
graphos/templates/graphos/c3js/js_base.html
graphos/templates/graphos/c3js/js_column.html
graphos/templates/graphos/c3js/js_donut.html
graphos/templates/graphos/c3js/js_pie.html
graphos/templates/graphos/flot/html.html
graphos/templates/graphos/flot/js.html
graphos/templates/graphos/flot/pie_chart.html
graphos/templates/graphos/gchart/area_chart.html
graphos/templates/graphos/gchart/bar_chart.html
graphos/templates/graphos/gchart/base.html
graphos/templates/graphos/gchart/candlestick_chart.html
graphos/templates/graphos/gchart/column_chart.html
graphos/templates/graphos/gchart/gauge_chart.html
graphos/templates/graphos/gchart/html.html
graphos/templates/graphos/gchart/line_chart.html
graphos/templates/graphos/gchart/pie_chart.html
graphos/templates/graphos/gchart/treemap_chart.html
graphos/templates/graphos/highcharts/html.html
graphos/templates/graphos/highcharts/js.html
graphos/templates/graphos/highcharts/js_dual_axis.html
graphos/templates/graphos/highcharts/js_heatmaps.html
graphos/templates/graphos/highcharts/js_highmaps.html
graphos/templates/graphos/highcharts/js_highmaps_multi_series.html
graphos/templates/graphos/highcharts/js_treemap.html
graphos/templates/graphos/matplotlib_renderer/line_chart.html
