Metadata-Version: 1.1
Name: django-graphos
Version: 0.3.41
Summary: Django app to provide a JS agnostic way to work with charts.
Home-page: http://github.com/agiliq/django-graphos
Author: Agiliq
Author-email: hello@agiliq.com
License: BSD
Platform: UNKNOWN
Classifier: Development Status :: 3 - Alpha
Classifier: Environment :: Web Environment
Classifier: Intended Audience :: Developers
Classifier: License :: OSI Approved :: BSD License
Classifier: Operating System :: OS Independent
Classifier: Programming Language :: Python
Classifier: Framework :: Django
